mkdocs_publisher/_cli/publisher.py
mkdocs_publisher/_cli/plugins/dev.py
mkdocs_publisher/_cli/plugins/md_tools.py
mkdocs_publisher/_extra/assets/__init__.py
mkdocs_publisher/_extra/assets/stylesheets/__init__.py
mkdocs_publisher/_extra/assets/stylesheets/blog.css
mkdocs_publisher/_extra/assets/stylesheets/blog.min.css
mkdocs_publisher/_extra/assets/stylesheets/blog.min.css.map
mkdocs_publisher/_extra/assets/stylesheets/obsidian.css
mkdocs_publisher/_extra/assets/stylesheets/obsidian.min.css
mkdocs_publisher/_extra/assets/stylesheets/obsidian.min.css.map
mkdocs_publisher/_extra/assets/templates/__init__.py
mkdocs_publisher/_extra/assets/templates/backlinks.html
mkdocs_publisher/_extra/assets/templates/posts-list.html
mkdocs_publisher/_extra/assets/templates/redirect.html
mkdocs_publisher/_shared/file_utils.py
mkdocs_publisher/_shared/html_modifiers.py
mkdocs_publisher/_shared/links.py
mkdocs_publisher/_shared/mkdocs_utils.py
mkdocs_publisher/_shared/publisher_utils.py
mkdocs_publisher/_shared/resources.py
mkdocs_publisher/_shared/templates.py
mkdocs_publisher/_shared/urls.py
mkdocs_publisher/blog/config.py
mkdocs_publisher/blog/creators.py
mkdocs_publisher/blog/modifiers.py
mkdocs_publisher/blog/parsers.py
mkdocs_publisher/blog/plugin.py
mkdocs_publisher/blog/structures.py
mkdocs_publisher/blog/translate.py
mkdocs_publisher/blog/lang/__init__.py
mkdocs_publisher/blog/lang/en.yaml
mkdocs_publisher/blog/lang/pl.yaml
mkdocs_publisher/debugger/config.py
mkdocs_publisher/debugger/loggers.py
mkdocs_publisher/debugger/plugin.py
mkdocs_publisher/meta/config.py
mkdocs_publisher/meta/meta_files.py
mkdocs_publisher/meta/meta_nav.py
mkdocs_publisher/meta/plugin.py
mkdocs_publisher/minifier/base.py
mkdocs_publisher/minifier/config.py
mkdocs_publisher/minifier/minifiers.py
mkdocs_publisher/minifier/plugin.py
mkdocs_publisher/obsidian/backlinks.py
mkdocs_publisher/obsidian/callouts.py
mkdocs_publisher/obsidian/config.py
mkdocs_publisher/obsidian/md_links.py
mkdocs_publisher-1.4.8.dist-info/METADATA
mkdocs_publisher-1.4.8.dist-info/WHEEL
mkdocs_publisher-1.4.8.dist-info/entry_points.txt
mkdocs_publisher-1.4.8.dist-info/licenses/LICENSE
mkdocs_publisher-1.4.8.dist-info/RECORD
