Metadata-Version: 2.4
Name: mkdocs-publisher
Version: 1.4.8
Summary: Publisher for MkDocs - set of plugins for content creators
Project-URL: Homepage, https://mkdocs-publisher.github.io/
Project-URL: Repository, https://github.com/mkdocs-publisher/mkdocs-publisher
Project-URL: Documentation, https://mkdocs-publisher.github.io/
Project-URL: Bug Tracker, https://github.com/mkdocs-publisher/mkdocs-publisher/issues
Author-email: Maciej 'maQ' Kusz <maciej.kusz@gmail.com>
License-Expression: MIT
License-File: LICENSE
Keywords: blog,categories,debugger,docs,documentation,frontmatter,markdown,minifier,mkdocs,mkdocs-plugin,navigation,obsidian,publisher,tags
Classifier: Development Status :: 5 - Production/Stable
Classifier: Environment :: Console
Classifier: Environment :: Web Environment
Classifier: Intended Audience :: Developers
Classifier: Intended Audience :: Education
Classifier: Intended Audience :: Information Technology
Classifier: Intended Audience :: Other Audience
Classifier: License :: OSI Approved :: MIT License
Classifier: Operating System :: OS Independent
Classifier: Programming Language :: Python
Classifier: Programming Language :: Python :: 3
Classifier: Programming Language :: Python :: 3 :: Only
Classifier: Programming Language :: Python :: 3.9
Classifier: Topic :: Documentation
Classifier: Topic :: Text Editors :: Documentation
Classifier: Topic :: Text Processing
Classifier: Topic :: Text Processing :: Markup
Classifier: Topic :: Text Processing :: Markup :: Markdown
Classifier: Topic :: Utilities
Requires-Python: >=3.9
Requires-Dist: beautifulsoup4>=4.13.4,~=4.0
Requires-Dist: colorama>=0.4.6
Requires-Dist: mkdocs-material>=9.6.15,~=9.0
Requires-Dist: mkdocs>=1.6.1,~=1.0
